profile_service/__init__.py
profile_service/main.py
devops_profile_service_project_2022-1.7.1.dist-info/METADATA
devops_profile_service_project_2022-1.7.1.dist-info/WHEEL
devops_profile_service_project_2022-1.7.1.dist-info/top_level.txt
devops_profile_service_project_2022-1.7.1.dist-info/RECORD
