Metadata-Version: 2.1
Name: devops-profile-service-project-2022
Version: 1.7.1
Summary: UNKNOWN
Home-page: UNKNOWN
License: UNKNOWN
Platform: UNKNOWN
Requires-Dist: fastapi
Requires-Dist: fastapi-contrib
Requires-Dist: sqlalchemy
Requires-Dist: uvicorn
Requires-Dist: pydantic
Requires-Dist: typing
Requires-Dist: psycopg2-binary
Requires-Dist: kafka-python
Requires-Dist: PyJWT
Requires-Dist: passlib
Requires-Dist: bcrypt
Requires-Dist: jaeger-client
Requires-Dist: opentracing
Requires-Dist: prometheus-fastapi-instrumentator
